bsw_code_gen/__init__.py
bsw_code_gen/cli.py
bsw_code_gen/generator.py
bsw_code_gen-0.1.14.dist-info/METADATA
bsw_code_gen-0.1.14.dist-info/WHEEL
bsw_code_gen-0.1.14.dist-info/entry_points.txt
bsw_code_gen-0.1.14.dist-info/top_level.txt
bsw_code_gen-0.1.14.dist-info/RECORD
