Metadata-Version: 2.1
Name: bsw_code_gen
Version: 0.1.14
Summary: Generic code generator used to generate C sources and headers of BSW modules
Home-page: https://github.com/openmcusw/bsw_code_gen
Author: Guillaume Sottas
Author-email: guillaumesottas@gmail.com
License: BSD-2 License
Requires-Dist: argparse
Requires-Dist: jsonschema
Requires-Dist: Jinja2
